fastbert/__init__.py
fastbert/config.py
fastbert/fastbert.py
fastbert/utils.py
fastbert/files/__init__.py
fastbert/files/google_bert_base_en.json
fastbert/files/google_bert_base_zh.json
fastbert/files/google_uncased_en_vocab.txt
fastbert/files/google_zh_vocab.txt
fastbert/files/uer_bert_large_zh.json
fastbert/files/uer_bert_small_zh.json
fastbert/files/uer_bert_tiny_zh.json
fastbert/uer/__init__.py
fastbert/uer/model_builder.py
fastbert/uer/model_loader.py
fastbert/uer/model_saver.py
fastbert/uer/trainer.py
fastbert/uer/encoders/__init__.py
fastbert/uer/encoders/attn_encoder.py
fastbert/uer/encoders/bert_encoder.py
fastbert/uer/encoders/birnn_encoder.py
fastbert/uer/encoders/cnn_encoder.py
fastbert/uer/encoders/gpt_encoder.py
fastbert/uer/encoders/mixed_encoder.py
fastbert/uer/encoders/rnn_encoder.py
fastbert/uer/encoders/synt_encoder.py
fastbert/uer/layers/__init__.py
fastbert/uer/layers/embeddings.py
fastbert/uer/layers/layer_norm.py
fastbert/uer/layers/multi_headed_attn.py
fastbert/uer/layers/multi_headed_attn_bak.py
fastbert/uer/layers/position_ffn.py
fastbert/uer/layers/synthesizer.py
fastbert/uer/layers/transformer.py
fastbert/uer/models/__init__.py
fastbert/uer/models/bert_model.py
fastbert/uer/models/model.py
fastbert/uer/subencoders/__init__.py
fastbert/uer/subencoders/avg_subencoder.py
fastbert/uer/subencoders/cnn_subencoder.py
fastbert/uer/subencoders/rnn_subencoder.py
fastbert/uer/targets/__init__.py
fastbert/uer/targets/bert_target.py
fastbert/uer/targets/bilm_target.py
fastbert/uer/targets/cls_target.py
fastbert/uer/targets/lm_target.py
fastbert/uer/targets/mlm_target.py
fastbert/uer/targets/nsp_target.py
fastbert/uer/targets/s2s_target.py
fastbert/uer/utils/__init__.py
fastbert/uer/utils/act_fun.py
fastbert/uer/utils/config.py
fastbert/uer/utils/constants.py
fastbert/uer/utils/data.py
fastbert/uer/utils/misc.py
fastbert/uer/utils/optimizers.py
fastbert/uer/utils/seed.py
fastbert/uer/utils/subword.py
fastbert/uer/utils/tokenizer.py
fastbert-0.2.2.dist-info/LICENSE
fastbert-0.2.2.dist-info/METADATA
fastbert-0.2.2.dist-info/WHEEL
fastbert-0.2.2.dist-info/top_level.txt
fastbert-0.2.2.dist-info/RECORD
