Metadata-Version: 2.1
Name: fastbert
Version: 0.2.2
Summary: The pipy version of FastBERT
Home-page: https://github.com/autoliuweijie/FastBERT
Author: Weijie Liu
Author-email: autoliuweijie@163.com
License: UNKNOWN
Platform: UNKNOWN
Classifier: Programming Language :: Python :: 3
Classifier: License :: OSI Approved :: MIT License
Classifier: Operating System :: OS Independent
Requires-Python: >=3.4
